bing_image_urls/__init__.py
bing_image_urls/bing_image_urls.py
bing_image_urls/get_image_size.py
bing_image_urls-0.1.3.dist-info/WHEEL
bing_image_urls-0.1.3.dist-info/METADATA
bing_image_urls-0.1.3.dist-info/RECORD
