Metadata-Version: 2.1
Name: bing-image-urls
Version: 0.1.3
Summary: fetch bing image urls based on keywords
Home-page: https://github.com/ffreemt/bing-image-urls
Author: ffreemt
Requires-Python: >=3.6,<4.0
Classifier: Programming Language :: Python :: 3
Classifier: Programming Language :: Python :: 3.6
Classifier: Programming Language :: Python :: 3.7
Classifier: Programming Language :: Python :: 3.8
Requires-Dist: httpx (>=0.15.5,<0.16.0)
Requires-Dist: logzero (>=1.5.0,<2.0.0)
Project-URL: Repository, https://github.com/ffreemt/bing-image-urls
